drug_couse/__init__.py
drug_couse/arm/__init__.py
drug_couse/arm/build.py
drug_couse-0.0.1.dist-info/METADATA
drug_couse-0.0.1.dist-info/WHEEL
drug_couse-0.0.1.dist-info/top_level.txt
drug_couse-0.0.1.dist-info/RECORD
