Metadata-Version: 2.4
Name: drug_couse
Version: 0.0.1
Summary: Analyze drug couse
Author-email: AshutoshGaur <ashutoshgaur@live.com>
Project-URL: homepage, https://ashugaur.github.io/drug_couse/
Project-URL: repository, https://github.com/ashugaur/drug_couse.git
Keywords: Associated rule mining,Pharma analytics,Patient analytics,Drug couse
Requires-Python: >=3.11
Requires-Dist: build>=1.2.2.post1
Requires-Dist: fastparquet>=2024.11.0
Requires-Dist: matplotlib>=3.10.3
Requires-Dist: mlxtend>=0.23.4
Requires-Dist: openpyxl>=3.1.5
Requires-Dist: pandas>=2.3.0
